fastmdui/__init__.py
fastmdui/components.py
fastmdui/core.py
fastmdui-0.1.3.dist-info/licenses/LICENSE
fastmdui-0.1.3.dist-info/METADATA
fastmdui-0.1.3.dist-info/WHEEL
fastmdui-0.1.3.dist-info/top_level.txt
fastmdui-0.1.3.dist-info/RECORD
