Metadata-Version: 2.4
Name: fastmdui
Version: 0.1.3
Summary: Material Design UI components for FastHTML
Home-page: https://github.com/seekerquest/fastmdui
Author: Lissan Zahid
Author-email: Lissan Zahid <lissane2013@duck.com>
License: MIT
Project-URL: Homepage, https://github.com/seekerquest/fastmdui
Project-URL: Documentation, https://github.com/seekerquest/fastmdui#readme
Project-URL: Repository, https://github.com/seekerquest/fastmdui
Classifier: Development Status :: 3 - Alpha
Classifier: Intended Audience :: Developers
Classifier: License :: OSI Approved :: MIT License
Classifier: Programming Language :: Python :: 3
Requires-Python: >=3.10
License-File: LICENSE
Requires-Dist: build>=1.4.0
Requires-Dist: python-fasthtml>=0.4.0
Requires-Dist: twine>=6.2.0
Dynamic: author
Dynamic: home-page
Dynamic: license-file
Dynamic: requires-python
